arctasks/__init__.py
arctasks/archive.py
arctasks/board.py
arctasks/doc.py
arctasks/interface.py
arctasks/jsonpy.py
arctasks/log.py
arctasks/main.py
arctasks/operations.py
arctasks/resolve.py
arc_tasks-0.1.2.dist-info/LICENSE
arc_tasks-0.1.2.dist-info/METADATA
arc_tasks-0.1.2.dist-info/WHEEL
arc_tasks-0.1.2.dist-info/entry_points.txt
arc_tasks-0.1.2.dist-info/top_level.txt
arc_tasks-0.1.2.dist-info/RECORD
