Metadata-Version: 2.1
Name: arc-tasks
Version: 0.1.2
Summary: Terminal task-objectives tracking, very handy with drop-down terminals.
Author-email: Predrag Bunic <noctdruid@proton.me>
License: GPLv3
Project-URL: Source, https://github.com/noctdruid/arc-tasks
Classifier: Programming Language :: Python :: 3
Classifier: Programming Language :: Python :: 3.8
Classifier: Programming Language :: Python :: 3.9
Classifier: Programming Language :: Python :: 3.10
Classifier: License :: OSI Approved :: GNU General Public License v3 (GPLv3)
Classifier: Operating System :: POSIX :: Linux
Requires-Python: >=3.8
License-File: LICENSE
